lumos/__init__.py
lumos/lumos.py
lumos/book/README.md
lumos/book/__init__.py
lumos/book/book_parser.py
lumos/book/doc_type.py
lumos/book/element_processor.py
lumos/book/markdown_utils.py
lumos/book/models.py
lumos/book/parser.py
lumos/book/pdf_utils.py
lumos/book/pyproject.toml
lumos/book/section_sorter.py
lumos/book/toc.py
lumos/book/toc_ai.py
lumos/book/visualizer.py
lumos/server/__init__.py
lumos/server/app.py
lumos/utils/cache.py
lumos/utils/client.py
lumos/utils/schema_utils.py
lumira_lumos-0.0.4.dist-info/METADATA
lumira_lumos-0.0.4.dist-info/WHEEL
lumira_lumos-0.0.4.dist-info/RECORD
