Metadata-Version: 2.4
Name: lumira-lumos
Version: 0.0.4
Author-email: Arun Patro <arun@lumiralabs.com>
Requires-Python: >=3.11
Requires-Dist: fastapi>=0.115.6
Requires-Dist: fire>=0.7.0
Requires-Dist: litellm>=1.58.2
Requires-Dist: pydantic>=2.10.5
Requires-Dist: python-magic>=0.4.27
Requires-Dist: rich>=13.9.4
Requires-Dist: structlog>=25.1.0
Requires-Dist: uvicorn>=0.34.0
Provides-Extra: book
Requires-Dist: pymupdf>=1.25.1; extra == 'book'
Requires-Dist: unstructured[pdf]>=0.16.13; extra == 'book'
Provides-Extra: dev
Requires-Dist: ipykernel>=6.29.5; extra == 'dev'
Requires-Dist: pre-commit>=4.0.1; extra == 'dev'
Requires-Dist: pytest>=8.3.4; extra == 'dev'
